CHANGES.rst
CONTRIBUTORS.rst
MANIFEST.in
README.rst
setup.cfg
setup.py
docs/LICENSE.GPL
docs/LICENSE.rst
docs/index.rst
src/noeku/__init__.py
src/noeku.linguacollage.egg-info/PKG-INFO
src/noeku.linguacollage.egg-info/SOURCES.txt
src/noeku.linguacollage.egg-info/dependency_links.txt
src/noeku.linguacollage.egg-info/entry_points.txt
src/noeku.linguacollage.egg-info/namespace_packages.txt
src/noeku.linguacollage.egg-info/not-zip-safe
src/noeku.linguacollage.egg-info/requires.txt
src/noeku.linguacollage.egg-info/top_level.txt
src/noeku/linguacollage/__init__.py
src/noeku/linguacollage/configure.zcml
src/noeku/linguacollage/interfaces.py
src/noeku/linguacollage/patches.py
src/noeku/linguacollage/setuphandlers.py
src/noeku/linguacollage/subscriber.py
src/noeku/linguacollage/testing.py
src/noeku/linguacollage/browser/__init__.py
src/noeku/linguacollage/browser/configure.zcml
src/noeku/linguacollage/browser/overrides/.gitkeep
src/noeku/linguacollage/browser/overrides/Products.Collage.browser.viewlets.delete.pt
src/noeku/linguacollage/browser/static/.gitkeep
src/noeku/linguacollage/locales/noeku.linguacollage.pot
src/noeku/linguacollage/locales/update.sh
src/noeku/linguacollage/locales/de/LC_MESSAGES/noeku.linguacollage.po
src/noeku/linguacollage/profiles/default/browserlayer.xml
src/noeku/linguacollage/profiles/default/metadata.xml
src/noeku/linguacollage/profiles/default/noekulinguacollage_default.txt
src/noeku/linguacollage/tests/__init__.py
src/noeku/linguacollage/tests/test_robot.py
src/noeku/linguacollage/tests/test_setup.py
src/noeku/linguacollage/tests/test_subscriber.py
src/noeku/linguacollage/tests/robot/test_example.robot